fastapi_middleware/__init__.py
fastapi_middleware/log.py
fastapi_middleware/utils.py
fastapi_middleware/middleware/__init__.py
fastapi_middleware/middleware/global_context.py
fastapi_middleware/middleware/sql.py
fastapi_middleware-0.2.0.dist-info/LICENCE
fastapi_middleware-0.2.0.dist-info/METADATA
fastapi_middleware-0.2.0.dist-info/WHEEL
fastapi_middleware-0.2.0.dist-info/top_level.txt
fastapi_middleware-0.2.0.dist-info/RECORD
