Metadata-Version: 2.1
Name: fastapi-middleware
Version: 0.2.0
Summary: Middleware for FastAPI
Home-page: https://github.com/Kholodnyi/fastapi-middleware
Author: Yurii Kholodnyi
Author-email: yurii.kholodnyi@gmail.com
Project-URL: Bug Tracker, https://github.com/Kholodnyi/fastapi-middleware/issues
Classifier: Programming Language :: Python :: 3
Classifier: Environment :: Web Environment
Classifier: Framework :: FastAPI
Classifier: License :: OSI Approved :: MIT License
Classifier: Operating System :: OS Independent
Requires-Python: >=3.8
License-File: LICENCE
Requires-Dist: fastapi
